aioapns/__init__.py
aioapns/client.py
aioapns/common.py
aioapns/connection.py
aioapns/exceptions.py
aioapns/logging.py
aioapns/py.typed
aioapns-4.0.dist-info/LICENSE
aioapns-4.0.dist-info/METADATA
aioapns-4.0.dist-info/WHEEL
aioapns-4.0.dist-info/top_level.txt
aioapns-4.0.dist-info/RECORD
